{
    "fluentMethods": true,
    "relationships": [],
    "fields": [
        {
            "fieldName": "fileName",
            "fieldType": "String",
            "fieldValidateRules": [
                "required"
            ]
        },
        {
            "fieldName": "size",
            "fieldType": "Long",
            "fieldValidateRules": [
                "required",
                "min"
            ],
            "fieldValidateRulesMin": "0"
        },
        {
            "fieldName": "lastModifiedDate",
            "fieldType": "ZonedDateTime",
            "fieldValidateRules": [
                "required"
            ]
        }
    ],
    "changelogDate": "20170319060102",
    "dto": "no",
    "service": "no",
    "entityTableName": "resource",
    "pagination": "pager"
}
